tb/tb_AXISFifo.v

`resetall
`timescale 1ns/1ps
`default_nettype none

module tb_AXISFIFO
(

);

  localparam DATA_WIDTH = 16;
  localparam ADDRESS_WIDTH = 2;
  reg clk;
  reg rst;
  reg [DATA_WIDTH-1:0] s_axis_0_tdata;
  reg s_axis_0_tvalid;
  wire s_axis_0_tready;
  reg s_axis_0_tlast;
  wire [DATA_WIDTH-1:0] m_axis_0_tdata;
  wire m_axis_0_tvalid;
  reg m_axis_0_tready;
  wire m_axis_0_tlast;
  reg reset_done;

  AXISFifo
  #(
    .DATA_WIDTH(DATA_WIDTH),
    .ADDRESS_WIDTH(ADDRESS_WIDTH)
  )
  uut
  (
    .clk(clk),
    .rst(rst),
    .s_axis_0_tdata(s_axis_0_tdata),
    .s_axis_0_tvalid(s_axis_0_tvalid),
    .s_axis_0_tready(s_axis_0_tready),
    .s_axis_0_tlast(s_axis_0_tlast),
    .m_axis_0_tdata(m_axis_0_tdata),
    .m_axis_0_tvalid(m_axis_0_tvalid),
    .m_axis_0_tready(m_axis_0_tready),
    .m_axis_0_tlast(m_axis_0_tlast)
  );


  initial begin
    $dumpfile("../vcd/tb_AXISFifo.vcd");
    $dumpvars(0, uut);
  end


  initial begin
    clk = 0;
    forever begin
      #1 clk = !clk;
    end
  end


  initial begin
    rst = 0;
    reset_done = 0;
    s_axis_0_tdata = 0;
    s_axis_0_tvalid = 0;
    s_axis_0_tlast = 0;
    m_axis_0_tready = 0;
    #10;
    rst = 1;
    #10;
    rst = 0;
    #10;
    count = 0;
    reset_done = 1;
    s_axis_0_tdata = -1;
    m_axis_0_tready = 1;
    timer = 2 ** ADDRESS_WIDTH - 1;
    @(posedge clk);
    #1;
  end

  integer count;
  integer count2;
  integer timer;

  always @(posedge clk) begin
    if(reset_done) begin
      $display("Count : %d -- %d:%d:%d:%X:%X:%X", (count - 1), s_axis_0_tready, s_axis_0_tvalid, s_axis_0_tlast, m_axis_0_tready, m_axis_0_tvalid, m_axis_0_tlast);
      if(s_axis_0_tready && s_axis_0_tvalid) begin
        count <= count + 1;
      end 
      if(!s_axis_0_tvalid && (count < 44)) begin
        s_axis_0_tvalid <= 1;
      end 
      if((count == 20 + 2 ** ADDRESS_WIDTH) || (count == 40)) begin
        s_axis_0_tlast <= 1;
      end 
      if((count < 1) && timer || s_axis_0_tready && s_axis_0_tlast || (count > 40)) begin
        s_axis_0_tlast <= 0;
        s_axis_0_tvalid <= 0;
      end 
      if((count > 40) && !timer) begin
        $finish;
      end 
      count2 <= count;
      if((count == count2) || !(s_axis_0_tvalid || m_axis_0_tready)) begin
        if(timer) begin
          timer <= timer - 1;
        end else begin
          timer <= 2 ** ADDRESS_WIDTH - 1;
        end
      end 
    end 
  end

  integer _tmp_0;

  always @(posedge clk) begin
    if(reset_done) begin
      _tmp_0 <= count % 4;
      case(_tmp_0)
        3: begin
          s_axis_0_tdata <= 47806;
        end
        2: begin
          s_axis_0_tdata <= 51966;
        end
        1: begin
          s_axis_0_tdata <= 48815;
        end
        default: begin
          s_axis_0_tdata <= 57005;
        end
      endcase
      if((count >= 21) && (count <= 21 + 2 ** ADDRESS_WIDTH + 1) && timer || (count >= 40 - 2 ** ADDRESS_WIDTH) && (count < 40) && timer || (count > 44)) begin
        m_axis_0_tready <= 0;
      end else if(!m_axis_0_tready) begin
        m_axis_0_tready <= 1;
      end 
    end 
  end


endmodule



module AXISFifo #
(
  parameter DATA_WIDTH = 16,
  parameter ADDRESS_WIDTH = 4
)
(
  input clk,
  input rst,
  input [DATA_WIDTH-1:0] s_axis_0_tdata,
  input s_axis_0_tvalid,
  output s_axis_0_tready,
  input s_axis_0_tlast,
  output [DATA_WIDTH-1:0] m_axis_0_tdata,
  output m_axis_0_tvalid,
  input m_axis_0_tready,
  output m_axis_0_tlast,
  output full,
  output almost_full,
  output empty,
  output almost_empty
);

  reg s_axis_0_tready_int;
  reg m_axis_0_tvalid_int;
  wire enq;
  wire deq;
  localparam EXP_ADDR_WIDTH = 2 ** ADDRESS_WIDTH - 1;
  reg [DATA_WIDTH:0] mem [0:EXP_ADDR_WIDTH];
  reg [ADDRESS_WIDTH-1:0] head;
  reg [ADDRESS_WIDTH-1:0] tail;
  wire is_empty;
  wire is_almost_empty;
  wire is_full;
  wire is_almost_full;
  assign is_empty = head == tail;
  assign is_almost_empty = head == (tail + 1 & EXP_ADDR_WIDTH);
  assign is_full = (head + 1 & EXP_ADDR_WIDTH) == tail;
  assign is_almost_full = (head + 2 & EXP_ADDR_WIDTH) == tail;
  assign full = is_full;
  assign almost_full = is_almost_full || is_full;
  assign empty = is_empty;
  assign almost_empty = is_almost_empty || is_empty;
  assign s_axis_0_tready = s_axis_0_tready_int;
  assign m_axis_0_tvalid = m_axis_0_tvalid_int;
  integer i;

  initial begin
    head = 0;
    tail = 0;
    for(i=0; i<=EXP_ADDR_WIDTH; i=i+1) begin
      mem[i] = 0;
    end
  end


  always @(*) begin
    if(rst) begin
      s_axis_0_tready_int <= 0;
      m_axis_0_tvalid_int <= 0;
    end else begin
      s_axis_0_tready_int <= !is_full;
      m_axis_0_tvalid_int <= !is_empty;
    end
  end

  assign enq = s_axis_0_tready_int && s_axis_0_tvalid;
  assign deq = m_axis_0_tvalid_int && m_axis_0_tready;
  assign { m_axis_0_tlast, m_axis_0_tdata } = mem[tail];

  always @(posedge clk) begin
    if(rst) begin
      head <= 0;
      tail <= 0;
    end else begin
      if(enq) begin
        mem[head] <= { s_axis_0_tlast, s_axis_0_tdata };
        head <= head + 1;
      end 
      if(deq) begin
        tail <= tail + 1;
      end 
    end
  end


endmodule

tb/tb_AXISBroadcaster.v

`resetall
`timescale 1ns/1ps
`default_nettype none

module tb_AXISBroadcaster
(

);

  localparam DATA_WIDTH = 16;
  localparam CHANNELS = 4;
  reg clk;
  reg rst;
  reg [DATA_WIDTH-1:0] s_axis_0_tdata;
  reg s_axis_0_tvalid;
  wire s_axis_0_tready;
  reg s_axis_0_tlast;
  wire [DATA_WIDTH*CHANNELS-1:0] m_axis_0_tdata;
  wire [CHANNELS-1:0] m_axis_0_tvalid;
  reg [CHANNELS-1:0] m_axis_0_tready;
  wire [CHANNELS-1:0] m_axis_0_tlast;
  reg reset_done;

  AXISBroadcaster
  #(
    .DATA_WIDTH(DATA_WIDTH),
    .CHANNELS(CHANNELS)
  )
  uut
  (
    .clk(clk),
    .rst(rst),
    .s_axis_0_tdata(s_axis_0_tdata),
    .s_axis_0_tvalid(s_axis_0_tvalid),
    .s_axis_0_tready(s_axis_0_tready),
    .s_axis_0_tlast(s_axis_0_tlast),
    .m_axis_0_tdata(m_axis_0_tdata),
    .m_axis_0_tvalid(m_axis_0_tvalid),
    .m_axis_0_tready(m_axis_0_tready),
    .m_axis_0_tlast(m_axis_0_tlast)
  );


  initial begin
    $dumpfile("../vcd/tb_AXISBroadcaster.vcd");
    $dumpvars(0, uut);
  end


  initial begin
    clk = 0;
    forever begin
      #1 clk = !clk;
    end
  end


  initial begin
    rst = 0;
    reset_done = 0;
    s_axis_0_tdata = 0;
    s_axis_0_tvalid = 0;
    s_axis_0_tlast = 0;
    m_axis_0_tready = 0;
    #10;
    rst = 1;
    #10;
    rst = 0;
    #10;
    count = 0;
    reset_done = 1;
    @(posedge clk);
    #1;
    m_axis_0_tready = -1;
    #500;
    $finish;
  end

  integer count;
  integer count2;
  integer timer;
  integer _tmp_0;

  always @(posedge clk) begin
    if(reset_done) begin
      $display("Count : %d -- %d:%d:%d:%X:%X:%X", count, s_axis_0_tready, s_axis_0_tvalid, s_axis_0_tlast, m_axis_0_tready, m_axis_0_tvalid, m_axis_0_tlast);
      if(s_axis_0_tready && s_axis_0_tvalid) begin
        count <= count + 1;
      end 
      _tmp_0 <= count % CHANNELS;
      case(_tmp_0)
        3: begin
          s_axis_0_tdata <= 57005;
        end
        2: begin
          s_axis_0_tdata <= 48815;
        end
        1: begin
          s_axis_0_tdata <= 51966;
        end
        default: begin
          s_axis_0_tdata <= 47806;
        end
      endcase
      if(!s_axis_0_tvalid && (count < 60)) begin
        s_axis_0_tvalid <= 1;
      end 
      if((count == 24) || (count == 52) || (count == 76)) begin
        s_axis_0_tlast <= 1;
      end 
      if(s_axis_0_tready && s_axis_0_tlast || (count > 84)) begin
        s_axis_0_tlast <= 0;
        s_axis_0_tvalid <= 0;
      end 
      if((count == 25) && m_axis_0_tvalid) begin
        s_axis_0_tvalid <= 0;
      end 
      if((count > 84) && !timer) begin
        $finish;
      end 
      count2 <= count;
      if((count == count2) || !(s_axis_0_tvalid || m_axis_0_tready)) begin
        if(timer) begin
          timer <= timer - 1;
        end else begin
          timer <= 3;
        end
      end else begin
        timer <= 3;
      end
    end 
  end

  genvar CHN;

  generate for(CHN=0; CHN<CHANNELS; CHN=CHN+1) begin

    always @(posedge clk) begin
      if(reset_done) begin
        if((count >= 21 + CHN) && (count < 21 + CHN + 2) && timer || (count >= 76 - CHN) && (count < 80 - CHN) && timer || (count > 84)) begin
          m_axis_0_tready[CHN] <= 0;
        end else begin
          m_axis_0_tready[CHN] <= 1;
        end
      end 
    end

  end
  endgenerate


endmodule



module AXISBroadcaster #
(
  parameter DATA_WIDTH = 16,
  parameter CHANNELS = 16
)
(
  input clk,
  input rst,
  input [DATA_WIDTH-1:0] s_axis_0_tdata,
  input s_axis_0_tvalid,
  output s_axis_0_tready,
  input s_axis_0_tlast,
  output [DATA_WIDTH*CHANNELS-1:0] m_axis_0_tdata,
  output [CHANNELS-1:0] m_axis_0_tvalid,
  input [CHANNELS-1:0] m_axis_0_tready,
  output [CHANNELS-1:0] m_axis_0_tlast
);

  localparam FIFO_DEPTH = 4;
  reg [DATA_WIDTH:0] data_reg;
  reg [CHANNELS-1:0] data_keep_reg;
  wire s_axis_0_tready_reg;
  wire [DATA_WIDTH:0] data_reg_next;
  wire [DATA_WIDTH:0] data_in_next;
  wire [CHANNELS-1:0] data_keep_next;
  wire [CHANNELS-1:0] data_keep_reg_next;
  wire [CHANNELS-1:0] data_keep_in_next;
  wire load_from_reg;
  wire load_from_in;
  wire input_handshake;
  assign load_from_reg = |data_keep_next;
  assign load_from_in = !load_from_reg;
  assign input_handshake = (load_from_in)? s_axis_0_tvalid & s_axis_0_tready_reg : 0;
  assign data_in_next = (input_handshake)? { s_axis_0_tlast, s_axis_0_tdata } : data_reg;
  assign data_reg_next = (load_from_reg)? data_reg : data_in_next;
  assign data_keep_in_next = (input_handshake)? -1 : data_keep_next;
  assign data_keep_reg_next = (load_from_reg)? data_keep_next : data_keep_in_next;
  assign s_axis_0_tready = s_axis_0_tready_reg;
  assign s_axis_0_tready_reg = (rst)? 0 : load_from_in;

  always @(posedge clk) begin
    if(rst) begin
      data_reg <= 0;
      data_keep_reg <= 0;
    end else begin
      data_reg <= data_reg_next;
      data_keep_reg <= data_keep_reg_next;
    end
  end

  genvar CHN;

  generate for(CHN=0; CHN<CHANNELS; CHN=CHN+1) begin
    reg [DATA_WIDTH-1:0] s_fifo_tdata;
    wire [DATA_WIDTH-1:0] m_fifo_tdata;
    wire s_fifo_tready;
    wire m_fifo_tready;
    wire s_fifo_tvalid;
    wire m_fifo_tvalid;
    wire s_fifo_tlast;
    wire m_fifo_tlast;
    wire s_fifo_handshake;
    wire m_fifo_handshake;

    always @(*) begin
      s_fifo_tdata <= data_reg[DATA_WIDTH-1:0];
    end

    assign s_fifo_tlast = data_reg[DATA_WIDTH];
    assign s_fifo_tvalid = data_keep_reg;
    assign s_fifo_handshake = s_fifo_tready && s_fifo_tvalid;
    assign data_keep_next[CHN] = (s_fifo_handshake)? 0 : s_fifo_tvalid;
    assign m_axis_0_tdata[DATA_WIDTH*(CHN+1)-1:DATA_WIDTH*CHN] = m_fifo_tdata;
    assign m_fifo_tready = m_axis_0_tready[CHN];
    assign m_axis_0_tvalid[CHN] = m_fifo_tvalid;
    assign m_axis_0_tlast[CHN] = m_fifo_tlast;

    AXISFifo
    #(
      .DATA_WIDTH(DATA_WIDTH),
      .ADDRESS_WIDTH($clog2(FIFO_DEPTH))
    )
    AXISFifo_inst_i
    (
      .clk(clk),
      .rst(rst),
      .s_axis_0_tdata(s_fifo_tdata),
      .s_axis_0_tvalid(s_fifo_tvalid),
      .s_axis_0_tready(s_fifo_tready),
      .s_axis_0_tlast(s_fifo_tlast),
      .m_axis_0_tdata(m_fifo_tdata),
      .m_axis_0_tvalid(m_fifo_tvalid),
      .m_axis_0_tready(m_fifo_tready),
      .m_axis_0_tlast(m_fifo_tlast)
    );

  end
  endgenerate


endmodule

`resetall

vcd/tb_AXISBroadcaster.vcd
$date
	Mon Sep 30 12:55:12 2024
$end
$version
	Icarus Verilog
$end
$timescale
	1ps
$end
$scope module tb_AXISBroadcaster $end
$scope module uut $end
$var wire 1 ! clk $end
$var wire 4 " m_axis_0_tready [3:0] $end
$var wire 1 # rst $end
$var wire 16 $ s_axis_0_tdata [15:0] $end
$var wire 1 % s_axis_0_tlast $end
$var wire 1 & s_axis_0_tready $end
$var wire 1 ' s_axis_0_tvalid $end
$var wire 1 ( s_axis_0_tready_reg $end
$var wire 4 ) m_axis_0_tvalid [3:0] $end
$var wire 4 * m_axis_0_tlast [3:0] $end
$var wire 64 + m_axis_0_tdata [63:0] $end
$var wire 1 , load_from_reg $end
$var wire 1 - load_from_in $end
$var wire 1 . input_handshake $end
$var wire 17 / data_reg_next [16:0] $end
$var wire 4 0 data_keep_reg_next [3:0] $end
$var wire 4 1 data_keep_next [3:0] $end
$var wire 4 2 data_keep_in_next [3:0] $end
$var wire 17 3 data_in_next [16:0] $end
$var reg 4 4 data_keep_reg [3:0] $end
$var reg 17 5 data_reg [16:0] $end
$scope begin genblk1[0] $end
$var wire 1 6 m_fifo_tready $end
$var wire 1 7 s_fifo_handshake $end
$var wire 1 8 s_fifo_tlast $end
$var wire 1 9 s_fifo_tvalid $end
$var wire 1 : s_fifo_tready $end
$var wire 1 ; m_fifo_tvalid $end
$var wire 1 < m_fifo_tlast $end
$var wire 16 = m_fifo_tdata [15:0] $end
$var reg 16 > s_fifo_tdata [15:0] $end
$scope module AXISFifo_inst_i $end
$var wire 1 ? almost_empty $end
$var wire 1 @ almost_full $end
$var wire 1 ! clk $end
$var wire 1 A deq $end
$var wire 1 B empty $end
$var wire 1 C enq $end
$var wire 1 D full $end
$var wire 1 6 m_axis_0_tready $end
$var wire 1 ; m_axis_0_tvalid $end
$var wire 1 # rst $end
$var wire 16 E s_axis_0_tdata [15:0] $end
$var wire 1 8 s_axis_0_tlast $end
$var wire 1 : s_axis_0_tready $end
$var wire 1 9 s_axis_0_tvalid $end
$var wire 1 < m_axis_0_tlast $end
$var wire 16 F m_axis_0_tdata [15:0] $end
$var wire 1 G is_full $end
$var wire 1 H is_empty $end
$var wire 1 I is_almost_full $end
$var wire 1 J is_almost_empty $end
$var reg 2 K head [1:0] $end
$var reg 1 L m_axis_0_tvalid_int $end
$var reg 1 M s_axis_0_tready_int $end
$var reg 2 N tail [1:0] $end
$var integer 32 O i [31:0] $end
$upscope $end
$upscope $end
$scope begin genblk1[1] $end
$var wire 1 P m_fifo_tready $end
$var wire 1 Q s_fifo_handshake $end
$var wire 1 R s_fifo_tlast $end
$var wire 1 S s_fifo_tvalid $end
$var wire 1 T s_fifo_tready $end
$var wire 1 U m_fifo_tvalid $end
$var wire 1 V m_fifo_tlast $end
$var wire 16 W m_fifo_tdata [15:0] $end
$var reg 16 X s_fifo_tdata [15:0] $end
$scope module AXISFifo_inst_i $end
$var wire 1 Y almost_empty $end
$var wire 1 Z almost_full $end
$var wire 1 ! clk $end
$var wire 1 [ deq $end
$var wire 1 \ empty $end
$var wire 1 ] enq $end
$var wire 1 ^ full $end
$var wire 1 P m_axis_0_tready $end
$var wire 1 U m_axis_0_tvalid $end
$var wire 1 # rst $end
$var wire 16 _ s_axis_0_tdata [15:0] $end
$var wire 1 R s_axis_0_tlast $end
$var wire 1 T s_axis_0_tready $end
$var wire 1 S s_axis_0_tvalid $end
$var wire 1 V m_axis_0_tlast $end
$var wire 16 ` m_axis_0_tdata [15:0] $end
$var wire 1 a is_full $end
$var wire 1 b is_empty $end
$var wire 1 c is_almost_full $end
$var wire 1 d is_almost_empty $end
$var reg 2 e head [1:0] $end
$var reg 1 f m_axis_0_tvalid_int $end
$var reg 1 g s_axis_0_tready_int $end
$var reg 2 h tail [1:0] $end
$var integer 32 i i [31:0] $end
$upscope $end
$upscope $end
$scope begin genblk1[2] $end
$var wire 1 j m_fifo_tready $end
$var wire 1 k s_fifo_handshake $end
$var wire 1 l s_fifo_tlast $end
$var wire 1 m s_fifo_tvalid $end
$var wire 1 n s_fifo_tready $end
$var wire 1 o m_fifo_tvalid $end
$var wire 1 p m_fifo_tlast $end
$var wire 16 q m_fifo_tdata [15:0] $end
$var reg 16 r s_fifo_tdata [15:0] $end
$scope module AXISFifo_inst_i $end
$var wire 1 s almost_empty $end
$var wire 1 t almost_full $end
$var wire 1 ! clk $end
$var wire 1 u deq $end
$var wire 1 v empty $end
$var wire 1 w enq $end
$var wire 1 x full $end
$var wire 1 j m_axis_0_tready $end
$var wire 1 o m_axis_0_tvalid $end
$var wire 1 # rst $end
$var wire 16 y s_axis_0_tdata [15:0] $end
$var wire 1 l s_axis_0_tlast $end
$var wire 1 n s_axis_0_tready $end
$var wire 1 m s_axis_0_tvalid $end
$var wire 1 p m_axis_0_tlast $end
$var wire 16 z m_axis_0_tdata [15:0] $end
$var wire 1 { is_full $end
$var wire 1 | is_empty $end
$var wire 1 } is_almost_full $end
$var wire 1 ~ is_almost_empty $end
$var reg 2 !" head [1:0] $end
$var reg 1 "" m_axis_0_tvalid_int $end
$var reg 1 #" s_axis_0_tready_int $end
$var reg 2 $" tail [1:0] $end
$var integer 32 %" i [31:0] $end
$upscope $end
$upscope $end
$scope begin genblk1[3] $end
$var wire 1 &" m_fifo_tready $end
$var wire 1 '" s_fifo_handshake $end
$var wire 1 (" s_fifo_tlast $end
$var wire 1 )" s_fifo_tvalid $end
$var wire 1 *" s_fifo_tready $end
$var wire 1 +" m_fifo_tvalid $end
$var wire 1 ," m_fifo_tlast $end
$var wire 16 -" m_fifo_tdata [15:0] $end
$var reg 16 ." s_fifo_tdata [15:0] $end
$scope module AXISFifo_inst_i $end
$var wire 1 /" almost_empty $end
$var wire 1 0" almost_full $end
$var wire 1 ! clk $end
$var wire 1 1" deq $end
$var wire 1 2" empty $end
$var wire 1 3" enq $end
$var wire 1 4" full $end
$var wire 1 &" m_axis_0_tready $end
$var wire 1 +" m_axis_0_tvalid $end
$var wire 1 # rst $end
$var wire 16 5" s_axis_0_tdata [15:0] $end
$var wire 1 (" s_axis_0_tlast $end
$var wire 1 *" s_axis_0_tready $end
$var wire 1 )" s_axis_0_tvalid $end
$var wire 1 ," m_axis_0_tlast $end
$var wire 16 6" m_axis_0_tdata [15:0] $end
$var wire 1 7" is_full $end
$var wire 1 8" is_empty $end
$var wire 1 9" is_almost_full $end
$var wire 1 :" is_almost_empty $end
$var reg 2 ;" head [1:0] $end
$var reg 1 <" m_axis_0_tvalid_int $end
$var reg 1 =" s_axis_0_tready_int $end
$var reg 2 >" tail [1:0] $end
$var integer 32 ?" i [31:0] $end
$upscope $end
$upscope $end
$upscope $end
$upscope $end
$enddefinitions $end
#0
$dumpvars
b100 ?"
b0 >"
1="
0<"
b0 ;"
0:"
09"
18"
07"
b0 6"
bx 5"
04"
x3"
12"
01"
00"
1/"
bx ."
b0 -"
0,"
0+"
1*"
x)"
x("
x'"
0&"
b100 %"
b0 $"
1#"
0""
b0 !"
0~
0}
1|
0{
b0 z
bx y
0x
xw
1v
0u
0t
1s
bx r
b0 q
0p
0o
1n
xm
xl
xk
0j
b100 i
b0 h
1g
0f
b0 e
0d
0c
1b
0a
b0 `
bx _
0^
x]
1\
0[
0Z
1Y
bx X
b0 W
0V
0U
1T
xS
xR
xQ
0P
b100 O
b0 N
1M
0L
b0 K
0J
0I
1H
0G
b0 F
bx E
0D
xC
1B
0A
0@
1?
bx >
b0 =
0<
0;
1:
x9
x8
x7
06
bx 5
bx 4
bx 3
bx 2
bx 1
bx 0
bx /
0.
x-
x,
b0 +
b0 *
b0 )
x(
0'
x&
0%
b0 $
0#
b0 "
0!
$end
#1000000000000
1!
#2000000000000
0!
#3000000000000
1!
#4000000000000
0!
#5000000000000
1!
#6000000000000
0!
#7000000000000
1!
#8000000000000
0!
#9000000000000
1!
#10000000000000
0C
07
0]
0Q
0w
0k
03"
0'"
0:
0M
0T
0g
0n
0#"
0*"
0="
0&
0(
0!
1#
#11000000000000
b0 ."
b0 5"
b0 r
b0 y
b0 X
b0 _
b0 >
b0 E
b0 0
b0 2
1-
0,
b0 1
b0 /
09
0S
0m
0)"
08
0R
0l
0("
b0 3
b0 4
b0 5
1!
#12000000000000
0!
#13000000000000
1!
#14000000000000
0!
#15000000000000
1!
#16000000000000
0!
#17000000000000
1!
#18000000000000
0!
#19000000000000
1!
#20000000000000
1:
1M
1T
1g
1n
1#"
1*"
1="
1&
1(
0!
0#
#21000000000000
1!
#22000000000000
0!
#23000000000000
1!
#24000000000000
0!
#25000000000000
1!
#26000000000000
0!
#27000000000000
1!
#28000000000000
0!
#29000000000000
1!
#30000000000000
0!
#31000000000000
b1011101010111110 /
b1111 0
b1011101010111110 3
b1111 2
1.
1&"
1j
1P
16
1'
b1011101010111110 $
b1111 "
1!
#32000000000000
0!
#33000000000000
b1011101010111110 >
b1011101010111110 E
b1011101010111110 X
b1011101010111110 _
b1011101010111110 r
b1011101010111110 y
b1011101010111110 ."
b1011101010111110 5"
b1111 0
b1111 2
1.
1&
1(
17
1C
1Q
1]
1k
1w
1'"
1-
0,
b0 1
13"
19
1S
1m
1)"
b1111 4
b1011101010111110 5
1!
#34000000000000
0!
#35000000000000
11"
1u
1[
1A
1+"
1<"
1o
1""
1U
1f
b1111 )
1;
1L
b1011101010111110 -"
b1011101010111110 6"
b1011101010111110 q
b1011101010111110 z
b1011101010111110 W
b1011101010111110 `
b1011101010111110101110101011111010111010101111101011101010111110 +
b1011101010111110 =
b1011101010111110 F
02"
08"
1:"
b1 ;"
0v
0|
1~
b1 !"
0\
0b
1d
b1 e
0B
0H
1J
b1 K
1!
#36000000000000
0!
#37000000000000
b1100101011111110 /
1?
1Y
1s
1/"
b1100101011111110 3
b1 N
1J
b10 K
b1 h
1d
b10 e
b1 $"
1~
b10 !"
b1 >"
1:"
b10 ;"
b1100101011111110 $
1!
#38000000000000
0!
#39000000000000
b1100101011111110 ."
b1100101011111110 5"
b1100101011111110 r
b1100101011111110 y
b1100101011111110 X
b1100101011111110 _
b1100101011111110 >
b1100101011111110 E
b1011111010101111 /
b1011111010101111 3
1/"
1s
1Y
1?
b1011111010101111 $
b1100101011111110 5
b10 >"
1:"
b11 ;"
b10 $"
1~
b11 !"
b10 h
1d
b11 e
b10 N
1J
b11 K
1!
#40000000000000
0!
#41000000000000
b1011111010101111 >
b1011111010101111 E
b1011111010101111 X
b1011111010101111 _
b1011111010101111 r
b1011111010101111 y
b1011111010101111 ."
b1011111010101111 5"
b1101111010101101 /
b1100101011111110 =
b1100101011111110 F
1?
b1100101011111110 W
b1100101011111110 `
1Y
b1100101011111110 q
b1100101011111110 z
1s
b1100101011111110110010101111111011001010111111101100101011111110 +
b1100101011111110 -"
b1100101011111110 6"
1/"
b1101111010101101 3
b11 N
1J
b0 K
b11 h
1d
b0 e
b11 $"
1~
b0 !"
b11 >"
1:"
b0 ;"
b1011111010101111 5
b1101111010101101 $
1!
#42000000000000
0!
#43000000000000
b1101111010101101 ."
b1101111010101101 5"
b1101111010101101 r
b1101111010101101 y
b1101111010101101 X
b1101111010101101 _
b1101111010101101 >
b1101111010101101 E
b1011101010111110 /
b1011101010111110 3
b1011111010101111 -"
b1011111010101111 6"
1/"
b1011111010101111 q
b1011111010101111 z
1s
b1011111010101111 W
b1011111010101111 `
1Y
b1011111010101111101111101010111110111110101011111011111010101111 +
b1011111010101111 =
b1011111010101111 F
1?
b1011101010111110 $
b1101111010101101 5
b0 >"
1:"
b1 ;"
b0 $"
1~
b1 !"
b0 h
1d
b1 e
b0 N
1J
b1 K
1!
#44000000000000
0!
#45000000000000
b1011101010111110 >
b1011101010111110 E
b1011101010111110 X
b1011101010111110 _
b1011101010111110 r
b1011101010111110 y
b1011101010111110 ."
b1011101010111110 5"
b1100101011111110 /
b1101111010101101 =
b1101111010101101 F
1?
b1101111010101101 W
b1101111010101101 `
1Y
b1101111010101101 q
b1101111010101101 z
1s
b1101111010101101110111101010110111011110101011011101111010101101 +
b1101111010101101 -"
b1101111010101101 6"
1/"
b1100101011111110 3
b1 N
1J
b10 K
b1 h
1d
b10 e
b1 $"
1~
b10 !"
b1 >"
1:"
b10 ;"
b1011101010111110 5
b1100101011111110 $
1!
#46000000000000
0!
#47000000000000
b1100101011111110 ."
b1100101011111110 5"
b1100101011111110 r
b1100101011111110 y
b1100101011111110 X
b1100101011111110 _
b1100101011111110 >
b1100101011111110 E
b1011111010101111 /
b1011111010101111 3
b1011101010111110 -"
b1011101010111110 6"
1/"
b1011101010111110 q
b1011101010111110 z
1s
b1011101010111110 W
b1011101010111110 `
1Y
b1011101010111110101110101011111010111010101111101011101010111110 +
b1011101010111110 =
b1011101010111110 F
1?
b1011111010101111 $
b1100101011111110 5
b10 >"
1:"
b11 ;"
b10 $"
1~
b11 !"
b10 h
1d
b11 e
b10 N
1J
b11 K
1!
#48000000000000
0!
#49000000000000
b1011111010101111 >
b1011111010101111 E
b1011111010101111 X
b1011111010101111 _
b1011111010101111 r
b1011111010101111 y
b1011111010101111 ."
b1011111010101111 5"
b1101111010101101 /
b1100101011111110 =
b1100101011111110 F
1?
b1100101011111110 W
b1100101011111110 `
1Y
b1100101011111110 q
b1100101011111110 z
1s
b1100101011111110110010101111111011001010111111101100101011111110 +
b1100101011111110 -"
b1100101011111110 6"
1/"
b1101111010101101 3
b11 N
1J
b0 K
b11 h
1d
b0 e
b11 $"
1~
b0 !"
b11 >"
1:"
b0 ;"
b1011111010101111 5
b1101111010101101 $
1!
#50000000000000
0!
#51000000000000
b1101111010101101 ."
b1101111010101101 5"
b1101111010101101 r
b1101111010101101 y
b1101111010101101 X
b1101111010101101 _
b1101111010101101 >
b1101111010101101 E
b1011101010111110 /
b1011101010111110 3
b1011111010101111 -"
b1011111010101111 6"
1/"
b1011111010101111 q
b1011111010101111 z
1s
b1011111010101111 W
b1011111010101111 `
1Y
b1011111010101111101111101010111110111110101011111011111010101111 +
b1011111010101111 =
b1011111010101111 F
1?
b1011101010111110 $
b1101111010101101 5
b0 >"
1:"
b1 ;"
b0 $"
1~
b1 !"
b0 h
1d
b1 e
b0 N
1J
b1 K
1!
#52000000000000
0!
#53000000000000
b1011101010111110 >
b1011101010111110 E
b1011101010111110 X
b1011101010111110 _
b1011101010111110 r
b1011101010111110 y
b1011101010111110 ."
b1011101010111110 5"
b1100101011111110 /
b1101111010101101 =
b1101111010101101 F
1?
b1101111010101101 W
b1101111010101101 `
1Y
b1101111010101101 q
b1101111010101101 z
1s
b1101111010101101110111101010110111011110101011011101111010101101 +
b1101111010101101 -"
b1101111010101101 6"
1/"
b1100101011111110 3
b1 N
1J
b10 K
b1 h
1d
b10 e
b1 $"
1~
b10 !"
b1 >"
1:"
b10 ;"
b1011101010111110 5
b1100101011111110 $
1!
#54000000000000
0!
#55000000000000
b1100101011111110 ."
b1100101011111110 5"
b1100101011111110 r
b1100101011111110 y
b1100101011111110 X
b1100101011111110 _
b1100101011111110 >
b1100101011111110 E
b1011111010101111 /
b1011111010101111 3
b1011101010111110 -"
b1011101010111110 6"
1/"
b1011101010111110 q
b1011101010111110 z
1s
b1011101010111110 W
b1011101010111110 `
1Y
b1011101010111110101110101011111010111010101111101011101010111110 +
b1011101010111110 =
b1011101010111110 F
1?
b1011111010101111 $
b1100101011111110 5
b10 >"
1:"
b11 ;"
b10 $"
1~
b11 !"
b10 h
1d
b11 e
b10 N
1J
b11 K
1!
#56000000000000
0!
#57000000000000
b1011111010101111 >
b1011111010101111 E
b1011111010101111 X
b1011111010101111 _
b1011111010101111 r
b1011111010101111 y
b1011111010101111 ."
b1011111010101111 5"
b1101111010101101 /
b1100101011111110 =
b1100101011111110 F
1?
b1100101011111110 W
b1100101011111110 `
1Y
b1100101011111110 q
b1100101011111110 z
1s
b1100101011111110110010101111111011001010111111101100101011111110 +
b1100101011111110 -"
b1100101011111110 6"
1/"
b1101111010101101 3
b11 N
1J
b0 K
b11 h
1d
b0 e
b11 $"
1~
b0 !"
b11 >"
1:"
b0 ;"
b1011111010101111 5
b1101111010101101 $
1!
#58000000000000
0!
#59000000000000
b1101111010101101 ."
b1101111010101101 5"
b1101111010101101 r
b1101111010101101 y
b1101111010101101 X
b1101111010101101 _
b1101111010101101 >
b1101111010101101 E
b1011101010111110 /
b1011101010111110 3
b1011111010101111 -"
b1011111010101111 6"
1/"
b1011111010101111 q
b1011111010101111 z
1s
b1011111010101111 W
b1011111010101111 `
1Y
b1011111010101111101111101010111110111110101011111011111010101111 +
b1011111010101111 =
b1011111010101111 F
1?
b1011101010111110 $
b1101111010101101 5
b0 >"
1:"
b1 ;"
b0 $"
1~
b1 !"
b0 h
1d
b1 e
b0 N
1J
b1 K
1!
#60000000000000
0!
