tb/tb_AXISFifo.v

`resetall
`timescale 1ns/1ps
`default_nettype none

module tb_AXISFIFO
(

);

  localparam DATA_WIDTH = 16;
  localparam ADDRESS_WIDTH = 2;
  reg clk;
  reg rst;
  reg [DATA_WIDTH-1:0] s_axis_0_tdata;
  reg s_axis_0_tvalid;
  wire s_axis_0_tready;
  reg s_axis_0_tlast;
  wire [DATA_WIDTH-1:0] m_axis_0_tdata;
  wire m_axis_0_tvalid;
  reg m_axis_0_tready;
  wire m_axis_0_tlast;
  reg reset_done;

  AXISFifo
  #(
    .DATA_WIDTH(DATA_WIDTH),
    .ADDRESS_WIDTH(ADDRESS_WIDTH)
  )
  uut
  (
    .clk(clk),
    .rst(rst),
    .s_axis_0_tdata(s_axis_0_tdata),
    .s_axis_0_tvalid(s_axis_0_tvalid),
    .s_axis_0_tready(s_axis_0_tready),
    .s_axis_0_tlast(s_axis_0_tlast),
    .m_axis_0_tdata(m_axis_0_tdata),
    .m_axis_0_tvalid(m_axis_0_tvalid),
    .m_axis_0_tready(m_axis_0_tready),
    .m_axis_0_tlast(m_axis_0_tlast)
  );


  initial begin
    $dumpfile("../vcd/tb_AXISFifo.vcd");
    $dumpvars(0, uut);
  end


  initial begin
    clk = 0;
    forever begin
      #1 clk = !clk;
    end
  end


  initial begin
    rst = 0;
    reset_done = 0;
    s_axis_0_tdata = 0;
    s_axis_0_tvalid = 0;
    s_axis_0_tlast = 0;
    m_axis_0_tready = 0;
    #10;
    rst = 1;
    #10;
    rst = 0;
    #10;
    count = 0;
    reset_done = 1;
    s_axis_0_tdata = -1;
    m_axis_0_tready = 1;
    timer = 2 ** ADDRESS_WIDTH - 1;
    @(posedge clk);
    #1;
  end

  integer count;
  integer count2;
  integer timer;

  always @(posedge clk) begin
    if(reset_done) begin
      $display("Count : %d -- %d:%d:%d:%X:%X:%X", (count - 1), s_axis_0_tready, s_axis_0_tvalid, s_axis_0_tlast, m_axis_0_tready, m_axis_0_tvalid, m_axis_0_tlast);
      if(s_axis_0_tready && s_axis_0_tvalid) begin
        count <= count + 1;
      end 
      if(!s_axis_0_tvalid && (count < 44)) begin
        s_axis_0_tvalid <= 1;
      end 
      if((count == 20 + 2 ** ADDRESS_WIDTH) || (count == 40)) begin
        s_axis_0_tlast <= 1;
      end 
      if((count < 1) && timer || s_axis_0_tready && s_axis_0_tlast || (count > 40)) begin
        s_axis_0_tlast <= 0;
        s_axis_0_tvalid <= 0;
      end 
      if((count > 40) && !timer) begin
        $finish;
      end 
      count2 <= count;
      if((count == count2) || !(s_axis_0_tvalid || m_axis_0_tready)) begin
        if(timer) begin
          timer <= timer - 1;
        end else begin
          timer <= 2 ** ADDRESS_WIDTH - 1;
        end
      end 
    end 
  end

  integer _tmp_0;

  always @(posedge clk) begin
    if(reset_done) begin
      _tmp_0 <= count % 4;
      case(_tmp_0)
        3: begin
          s_axis_0_tdata <= 47806;
        end
        2: begin
          s_axis_0_tdata <= 51966;
        end
        1: begin
          s_axis_0_tdata <= 48815;
        end
        default: begin
          s_axis_0_tdata <= 57005;
        end
      endcase
      if((count >= 21) && (count <= 21 + 2 ** ADDRESS_WIDTH + 1) && timer || (count >= 40 - 2 ** ADDRESS_WIDTH) && (count < 40) && timer || (count > 44)) begin
        m_axis_0_tready <= 0;
      end else if(!m_axis_0_tready) begin
        m_axis_0_tready <= 1;
      end 
    end 
  end


endmodule



module AXISFifo #
(
  parameter DATA_WIDTH = 16,
  parameter ADDRESS_WIDTH = 4
)
(
  input clk,
  input rst,
  input [DATA_WIDTH-1:0] s_axis_0_tdata,
  input s_axis_0_tvalid,
  output s_axis_0_tready,
  input s_axis_0_tlast,
  output [DATA_WIDTH-1:0] m_axis_0_tdata,
  output m_axis_0_tvalid,
  input m_axis_0_tready,
  output m_axis_0_tlast,
  output full,
  output almost_full,
  output empty,
  output almost_empty
);

  reg s_axis_0_tready_int;
  reg m_axis_0_tvalid_int;
  wire enq;
  wire deq;
  localparam EXP_ADDR_WIDTH = 2 ** ADDRESS_WIDTH - 1;
  reg [DATA_WIDTH:0] mem [0:EXP_ADDR_WIDTH];
  reg [ADDRESS_WIDTH-1:0] head;
  reg [ADDRESS_WIDTH-1:0] tail;
  wire is_empty;
  wire is_almost_empty;
  wire is_full;
  wire is_almost_full;
  assign is_empty = head == tail;
  assign is_almost_empty = head == (tail + 1 & EXP_ADDR_WIDTH);
  assign is_full = (head + 1 & EXP_ADDR_WIDTH) == tail;
  assign is_almost_full = (head + 2 & EXP_ADDR_WIDTH) == tail;
  assign full = is_full;
  assign almost_full = is_almost_full || is_full;
  assign empty = is_empty;
  assign almost_empty = is_almost_empty || is_empty;
  assign s_axis_0_tready = s_axis_0_tready_int;
  assign m_axis_0_tvalid = m_axis_0_tvalid_int;
  integer i;

  initial begin
    head = 0;
    tail = 0;
    for(i=0; i<=EXP_ADDR_WIDTH; i=i+1) begin
      mem[i] = 0;
    end
  end


  always @(*) begin
    if(rst) begin
      s_axis_0_tready_int <= 0;
      m_axis_0_tvalid_int <= 0;
    end else begin
      s_axis_0_tready_int <= !is_full;
      m_axis_0_tvalid_int <= !is_empty;
    end
  end

  assign enq = s_axis_0_tready_int && s_axis_0_tvalid;
  assign deq = m_axis_0_tvalid_int && m_axis_0_tready;
  assign { m_axis_0_tlast, m_axis_0_tdata } = mem[tail];

  always @(posedge clk) begin
    if(rst) begin
      head <= 0;
      tail <= 0;
    end else begin
      if(enq) begin
        mem[head] <= { s_axis_0_tlast, s_axis_0_tdata };
        head <= head + 1;
      end 
      if(deq) begin
        tail <= tail + 1;
      end 
    end
  end


endmodule

vcd/tb_AXISFifo.vcd
$date
	Fri Sep 27 12:39:29 2024
$end
$version
	Icarus Verilog
$end
$timescale
	1s
$end
$scope module tb_AXISFIFO $end
$scope module uut $end
$var wire 1 ! almost_empty $end
$var wire 1 " almost_full $end
$var wire 1 # clk $end
$var wire 1 $ deq $end
$var wire 1 % empty $end
$var wire 1 & enq $end
$var wire 1 ' full $end
$var wire 1 ( m_axis_0_tready $end
$var wire 1 ) m_axis_0_tvalid $end
$var wire 1 * rst $end
$var wire 16 + s_axis_0_tdata [15:0] $end
$var wire 1 , s_axis_0_tlast $end
$var wire 1 - s_axis_0_tready $end
$var wire 1 . s_axis_0_tvalid $end
$var wire 1 / m_axis_0_tlast $end
$var wire 16 0 m_axis_0_tdata [15:0] $end
$var wire 1 1 is_full $end
$var wire 1 2 is_empty $end
$var wire 1 3 is_almost_full $end
$var wire 1 4 is_almost_empty $end
$var reg 2 5 head [1:0] $end
$var reg 1 6 m_axis_0_tvalid_int $end
$var reg 1 7 s_axis_0_tready_int $end
$var reg 2 8 tail [1:0] $end
$var integer 32 9 i [31:0] $end
$upscope $end
$upscope $end
$enddefinitions $end
#0
$dumpvars
b100 9
b0 8
17
06
b0 5
04
03
12
01
b0 0
0/
0.
1-
0,
b0 +
0*
0)
0(
0'
0&
1%
0$
0#
0"
1!
$end
#1
1#
#2
0#
#3
1#
#4
0#
#5
1#
#6
0#
#7
1#
#8
0#
#9
1#
#10
0-
07
0#
1*
#11
1#
#12
0#
#13
1#
#14
0#
#15
1#
#16
0#
#17
1#
#18
0#
#19
1#
#20
1-
17
0#
0*
#21
1#
#22
0#
#23
1#
#24
0#
#25
1#
#26
0#
#27
1#
#28
0#
#29
1#
#30
0#
1(
b1111111111111111 +
#31
b1101111010101101 +
0.
1#
#32
0#
#33
0.
1#
#34
0#
#35
0.
1#
#36
0#
#37
0.
1#
#38
0#
#39
1&
1.
1#
#40
0#
#41
1$
1)
16
b1101111010101101 0
0&
0%
02
14
b1 5
0.
1#
#42
0#
#43
0$
0)
06
1&
04
b0 0
1.
1%
12
b1 8
1#
#44
0#
#45
1$
1)
16
b1101111010101101 0
0%
02
14
b10 5
b1011111010101111 +
1#
#46
0#
#47
b1011111010101111 0
1!
b10 8
14
b11 5
1#
#48
0#
#49
1!
b11 8
14
b0 5
b1100101011111110 +
1#
#50
0#
#51
b1100101011111110 0
1!
b1011101010111110 +
b0 8
14
b1 5
1#
#52
0#
#53
b1011101010111110 0
1!
b1 8
14
b10 5
b1101111010101101 +
1#
#54
0#
#55
b1101111010101101 0
1!
b1011111010101111 +
b10 8
14
b11 5
1#
#56
0#
#57
b1011111010101111 0
1!
b11 8
14
b0 5
b1100101011111110 +
1#
#58
0#
#59
b1100101011111110 0
1!
b1011101010111110 +
b0 8
14
b1 5
1#
#60
0#
#61
b1011101010111110 0
1!
b1 8
14
b10 5
b1101111010101101 +
1#
#62
0#
#63
b1101111010101101 0
1!
b1011111010101111 +
b10 8
14
b11 5
1#
#64
0#
#65
b1011111010101111 0
1!
b11 8
14
b0 5
b1100101011111110 +
1#
#66
0#
#67
b1100101011111110 0
1!
b1011101010111110 +
b0 8
14
b1 5
1#
#68
0#
#69
b1011101010111110 0
1!
b1 8
14
b10 5
b1101111010101101 +
1#
#70
0#
#71
b1101111010101101 0
1!
b1011111010101111 +
b10 8
14
b11 5
1#
#72
0#
#73
b1011111010101111 0
1!
b11 8
14
b0 5
b1100101011111110 +
1#
#74
0#
#75
b1100101011111110 0
1!
b1011101010111110 +
b0 8
14
b1 5
1#
#76
0#
#77
b1011101010111110 0
1!
b1 8
14
b10 5
b1101111010101101 +
1#
#78
0#
#79
b1101111010101101 0
1!
b1011111010101111 +
b10 8
14
b11 5
1#
#80
0#
#81
b1011111010101111 0
1!
b11 8
14
b0 5
b1100101011111110 +
1#
#82
0#
#83
b1100101011111110 0
1!
b1011101010111110 +
b0 8
14
b1 5
1#
#84
0#
#85
b1011101010111110 0
1!
0$
b1 8
14
b10 5
0(
b1101111010101101 +
1#
#86
0#
#87
1"
0!
13
b1011111010101111 +
04
b11 5
1#
#88
0#
#89
0&
0-
07
1'
11
03
b0 5
b1100101011111110 +
1#
#90
0#
#91
b1011101010111110 +
1,
1#
#92
0#
#93
b1101111010101101 +
1#
#94
0#
#95
1$
1(
1#
#96
0#
#97
1&
1-
17
b1101111010101101 0
0$
0'
01
13
b10 8
0(
1#
#98
0#
#99
0-
07
0&
1'
11
03
0.
0,
b1 5
1#
#100
0#
#101
1.
1#
#102
0#
#103
1$
1(
b1011111010101111 +
1#
#104
0#
#105
1&
1-
17
b1011111010101111 0
0$
0'
01
13
b11 8
0(
1#
#106
0#
#107
0&
0-
07
1'
11
03
b10 5
1#
#108
0#
#109
1#
#110
0#
#111
b1100101011111110 +
1#
#112
0#
#113
1$
1(
1#
#114
0#
#115
1&
1-
17
0$
1/
b1101111010101101 0
0(
0'
01
13
b0 8
1#
#116
0#
#117
0&
0-
07
1'
11
03
b11 5
1#
#118
0#
#119
1$
1(
1#
#120
0#
#121
1&
1-
17
0/
b1011111010101111 0
0'
01
13
b1 8
b1011101010111110 +
1#
#122
0#
#123
b1100101011111110 0
13
b10 8
b0 5
1#
#124
0#
#125
b1011101010111110 0
13
b11 8
b1 5
1#
#126
0#
#127
b1101111010101101 +
13
b0 8
b10 5
1#
#128
0#
#129
13
b1 8
b11 5
b1011111010101111 +
1#
#130
0#
#131
b1101111010101101 0
b1100101011111110 +
13
b10 8
b0 5
1#
#132
0#
#133
b1011111010101111 0
13
b11 8
b1 5
b1011101010111110 +
1#
#134
0#
#135
b1100101011111110 0
b1101111010101101 +
13
b0 8
b10 5
1#
#136
0#
#137
b1011101010111110 0
13
b1 8
b11 5
b1011111010101111 +
1#
#138
0#
#139
b1101111010101101 0
b1100101011111110 +
13
b10 8
b0 5
1#
#140
0#
#141
b1011111010101111 0
0$
13
b11 8
b1 5
0(
b1011101010111110 +
1#
#142
0#
#143
0&
0-
07
1'
11
03
b1101111010101101 +
b10 5
1#
#144
0#
#145
b1011111010101111 +
1#
#146
0#
#147
b1100101011111110 +
1#
#148
0#
#149
1#
#150
0#
#151
1#
#152
0#
#153
1$
1(
1#
#154
0#
#155
1&
1-
17
0$
b1100101011111110 0
0(
0'
01
13
b0 8
1#
#156
0#
#157
0&
0-
07
1'
11
03
b11 5
1#
#158
0#
#159
1#
#160
0#
#161
b1011101010111110 +
1#
#162
0#
#163
1$
1(
1#
#164
0#
#165
1&
1-
17
b1011101010111110 0
0$
0'
01
13
b1 8
0(
1#
#166
0#
#167
0&
0-
07
1'
11
03
b0 5
1#
#168
0#
#169
1$
1,
1(
1#
#170
0#
#171
1&
1-
17
b1100101011111110 0
b1101111010101101 +
0'
01
13
b10 8
1#
#172
0#
#173
b1011101010111110 0
0&
13
b11 8
b1 5
0.
0,
1#
#174
0#
#175
1!
14
0"
1/
b1101111010101101 0
0.
03
b0 8
1#
#176
0#
#177
0$
0)
06
04
0/
b1011101010111110 0
1%
12
b1 8
0.
b1011111010101111 +
1#
#178
0#
#179
0.
1#
#180
0#
#181
0.
1#
#182
0#
#183
0.
1#
